littleblog/__init__.py
littleblog/cli.py
littleblog/little.py
littleblog/skel/settings.py
littleblog/skel/static/code.css
littleblog/skel/templates/base.html
littleblog/skel/templates/detail.html
littleblog/skel/templates/list.html
littleblog-0.3.1.dist-info/DESCRIPTION.rst
littleblog-0.3.1.dist-info/METADATA
littleblog-0.3.1.dist-info/RECORD
littleblog-0.3.1.dist-info/WHEEL
littleblog-0.3.1.dist-info/entry_points.txt
littleblog-0.3.1.dist-info/metadata.json
littleblog-0.3.1.dist-info/top_level.txt
