Metadata-Version: 2.0
Name: littleblog
Version: 0.3.1
Summary: littleblog - a simple static site generator
Home-page: https://github.com/wookalar/littleblog
Author: Aaron Hampton
Author-email: aaron.hampt@gmail.com
License: AGPLv3
Platform: UNKNOWN
Requires-Dist: click (>=6.6)
Requires-Dist: Jinja2 (>=2.8)
Requires-Dist: Markdown (>=2.6.8)
Requires-Dist: MarkupSafe (>=0.23)
Requires-Dist: Pygments (>=2.1.3)
